djp_sepa/.gitignore
djp_sepa/__init__.py
djp_sepa/apps.py
djp_sepa/forms.py
djp_sepa/locale/de_DE/LC_MESSAGES/django.po
djp_sepa/migrations/0001_initial.py
djp_sepa/migrations/0002_sepamandate_mandate_id.py
djp_sepa/migrations/__init__.py
djp_sepa/models.py
djp_sepa/providers.py
django_payments_sepa-2.0.0.dist-info/LICENSE
django_payments_sepa-2.0.0.dist-info/METADATA
django_payments_sepa-2.0.0.dist-info/WHEEL
django_payments_sepa-2.0.0.dist-info/RECORD
